{
    "create_time": 1773386480,
    "juan": [
        {
            "juan_int": "1",
            "title": "素问",
            "zhang_jie": [
                {
                    "id": "1",
                    "juan_int": "1",
                    "juan_name": "素问",
                    "zhang_jie_int": "1",
                    "zhang_jie_name": "上古天真论"
                },
                {
                    "id": "2",
                    "juan_int": "1",
                    "juan_name": "素问",
                    "zhang_jie_int": "2",
                    "zhang_jie_name": "四气调神大论"
                },
                {
                    "id": "3",
                    "juan_int": "1",
                    "juan_name": "素问",
                    "zhang_jie_int": "3",
                    "zhang_jie_name": "生气通天论"
                },
                {
                    "id": "4",
                    "juan_int": "1",
                    "juan_name": "素问",
                    "zhang_jie_int": "4",
                    "zhang_jie_name": "金匮真言论"
                },
                {
                    "id": "5",
                    "juan_int": "1",
                    "juan_name": "素问",
                    "zhang_jie_int": "5",
                    "zhang_jie_name": "阴阳应象大论"
                },
                {
                    "id": "6",
                    "juan_int": "1",
                    "juan_name": "素问",
                    "zhang_jie_int": "6",
                    "zhang_jie_name": "阴阳离合论"
                },
                {
                    "id": "7",
                    "juan_int": "1",
                    "juan_name": "素问",
                    "zhang_jie_int": "7",
                    "zhang_jie_name": "阴阳别论"
                },
                {
                    "id": "8",
                    "juan_int": "1",
                    "juan_name": "素问",
                    "zhang_jie_int": "8",
                    "zhang_jie_name": "灵兰秘典论"
                },
                {
                    "id": "9",
                    "juan_int": "1",
                    "juan_name": "素问",
                    "zhang_jie_int": "9",
                    "zhang_jie_name": "六节藏象论"
                },
                {
                    "id": "10",
                    "juan_int": "1",
                    "juan_name": "素问",
                    "zhang_jie_int": "10",
                    "zhang_jie_name": "五藏生成"
                },
                {
                    "id": "11",
                    "juan_int": "1",
                    "juan_name": "素问",
                    "zhang_jie_int": "11",
                    "zhang_jie_name": "五藏别论"
                },
                {
                    "id": "12",
                    "juan_int": "1",
                    "juan_name": "素问",
                    "zhang_jie_int": "12",
                    "zhang_jie_name": "异法方宜论"
                },
                {
                    "id": "13",
                    "juan_int": "1",
                    "juan_name": "素问",
                    "zhang_jie_int": "13",
                    "zhang_jie_name": "移精变气论"
                },
                {
                    "id": "14",
                    "juan_int": "1",
                    "juan_name": "素问",
                    "zhang_jie_int": "14",
                    "zhang_jie_name": "汤液醪醴论"
                },
                {
                    "id": "15",
                    "juan_int": "1",
                    "juan_name": "素问",
                    "zhang_jie_int": "15",
                    "zhang_jie_name": "玉版论要"
                },
                {
                    "id": "16",
                    "juan_int": "1",
                    "juan_name": "素问",
                    "zhang_jie_int": "16",
                    "zhang_jie_name": "诊要经终论"
                },
                {
                    "id": "17",
                    "juan_int": "1",
                    "juan_name": "素问",
                    "zhang_jie_int": "17",
                    "zhang_jie_name": "脉要精微论"
                },
                {
                    "id": "18",
                    "juan_int": "1",
                    "juan_name": "素问",
                    "zhang_jie_int": "18",
                    "zhang_jie_name": "平人气象论"
                },
                {
                    "id": "19",
                    "juan_int": "1",
                    "juan_name": "素问",
                    "zhang_jie_int": "19",
                    "zhang_jie_name": "玉机真藏论"
                },
                {
                    "id": "20",
                    "juan_int": "1",
                    "juan_name": "素问",
                    "zhang_jie_int": "20",
                    "zhang_jie_name": "三部九候论"
                },
                {
                    "id": "21",
                    "juan_int": "1",
                    "juan_name": "素问",
                    "zhang_jie_int": "21",
                    "zhang_jie_name": "经脉别论"
                },
                {
                    "id": "22",
                    "juan_int": "1",
                    "juan_name": "素问",
                    "zhang_jie_int": "22",
                    "zhang_jie_name": "藏气法时论"
                },
                {
                    "id": "23",
                    "juan_int": "1",
                    "juan_name": "素问",
                    "zhang_jie_int": "23",
                    "zhang_jie_name": "宣明五气"
                },
                {
                    "id": "24",
                    "juan_int": "1",
                    "juan_name": "素问",
                    "zhang_jie_int": "24",
                    "zhang_jie_name": "血气形志"
                },
                {
                    "id": "25",
                    "juan_int": "1",
                    "juan_name": "素问",
                    "zhang_jie_int": "25",
                    "zhang_jie_name": "宝命全形论"
                },
                {
                    "id": "26",
                    "juan_int": "1",
                    "juan_name": "素问",
                    "zhang_jie_int": "26",
                    "zhang_jie_name": "八正神明论"
                },
                {
                    "id": "27",
                    "juan_int": "1",
                    "juan_name": "素问",
                    "zhang_jie_int": "27",
                    "zhang_jie_name": "离合真邪论"
                },
                {
                    "id": "28",
                    "juan_int": "1",
                    "juan_name": "素问",
                    "zhang_jie_int": "28",
                    "zhang_jie_name": "通评虚实论"
                },
                {
                    "id": "29",
                    "juan_int": "1",
                    "juan_name": "素问",
                    "zhang_jie_int": "29",
                    "zhang_jie_name": "太阴阳明论"
                },
                {
                    "id": "30",
                    "juan_int": "1",
                    "juan_name": "素问",
                    "zhang_jie_int": "30",
                    "zhang_jie_name": "阳明脉解"
                },
                {
                    "id": "31",
                    "juan_int": "1",
                    "juan_name": "素问",
                    "zhang_jie_int": "31",
                    "zhang_jie_name": "热论"
                },
                {
                    "id": "32",
                    "juan_int": "1",
                    "juan_name": "素问",
                    "zhang_jie_int": "32",
                    "zhang_jie_name": "刺热"
                },
                {
                    "id": "33",
                    "juan_int": "1",
                    "juan_name": "素问",
                    "zhang_jie_int": "33",
                    "zhang_jie_name": "评热病论"
                },
                {
                    "id": "34",
                    "juan_int": "1",
                    "juan_name": "素问",
                    "zhang_jie_int": "34",
                    "zhang_jie_name": "逆调论"
                },
                {
                    "id": "35",
                    "juan_int": "1",
                    "juan_name": "素问",
                    "zhang_jie_int": "35",
                    "zhang_jie_name": "疟论"
                },
                {
                    "id": "36",
                    "juan_int": "1",
                    "juan_name": "素问",
                    "zhang_jie_int": "36",
                    "zhang_jie_name": "刺疟"
                },
                {
                    "id": "37",
                    "juan_int": "1",
                    "juan_name": "素问",
                    "zhang_jie_int": "37",
                    "zhang_jie_name": "气厥论"
                },
                {
                    "id": "38",
                    "juan_int": "1",
                    "juan_name": "素问",
                    "zhang_jie_int": "38",
                    "zhang_jie_name": "咳论"
                },
                {
                    "id": "39",
                    "juan_int": "1",
                    "juan_name": "素问",
                    "zhang_jie_int": "39",
                    "zhang_jie_name": "举痛论"
                },
                {
                    "id": "40",
                    "juan_int": "1",
                    "juan_name": "素问",
                    "zhang_jie_int": "40",
                    "zhang_jie_name": "腹中论"
                },
                {
                    "id": "41",
                    "juan_int": "1",
                    "juan_name": "素问",
                    "zhang_jie_int": "41",
                    "zhang_jie_name": "刺腰痛"
                },
                {
                    "id": "42",
                    "juan_int": "1",
                    "juan_name": "素问",
                    "zhang_jie_int": "42",
                    "zhang_jie_name": "风论"
                },
                {
                    "id": "43",
                    "juan_int": "1",
                    "juan_name": "素问",
                    "zhang_jie_int": "43",
                    "zhang_jie_name": "痹论"
                },
                {
                    "id": "44",
                    "juan_int": "1",
                    "juan_name": "素问",
                    "zhang_jie_int": "44",
                    "zhang_jie_name": "痿论"
                },
                {
                    "id": "45",
                    "juan_int": "1",
                    "juan_name": "素问",
                    "zhang_jie_int": "45",
                    "zhang_jie_name": "厥论"
                },
                {
                    "id": "46",
                    "juan_int": "1",
                    "juan_name": "素问",
                    "zhang_jie_int": "46",
                    "zhang_jie_name": "病能论"
                },
                {
                    "id": "47",
                    "juan_int": "1",
                    "juan_name": "素问",
                    "zhang_jie_int": "47",
                    "zhang_jie_name": "奇病论"
                },
                {
                    "id": "48",
                    "juan_int": "1",
                    "juan_name": "素问",
                    "zhang_jie_int": "48",
                    "zhang_jie_name": "大奇论"
                },
                {
                    "id": "49",
                    "juan_int": "1",
                    "juan_name": "素问",
                    "zhang_jie_int": "49",
                    "zhang_jie_name": "脉解"
                },
                {
                    "id": "50",
                    "juan_int": "1",
                    "juan_name": "素问",
                    "zhang_jie_int": "50",
                    "zhang_jie_name": "刺要论"
                },
                {
                    "id": "51",
                    "juan_int": "1",
                    "juan_name": "素问",
                    "zhang_jie_int": "51",
                    "zhang_jie_name": "刺齐论"
                },
                {
                    "id": "52",
                    "juan_int": "1",
                    "juan_name": "素问",
                    "zhang_jie_int": "52",
                    "zhang_jie_name": "刺禁论"
                },
                {
                    "id": "53",
                    "juan_int": "1",
                    "juan_name": "素问",
                    "zhang_jie_int": "53",
                    "zhang_jie_name": "刺志论"
                },
                {
                    "id": "54",
                    "juan_int": "1",
                    "juan_name": "素问",
                    "zhang_jie_int": "54",
                    "zhang_jie_name": "针解"
                },
                {
                    "id": "55",
                    "juan_int": "1",
                    "juan_name": "素问",
                    "zhang_jie_int": "55",
                    "zhang_jie_name": "长刺节论"
                },
                {
                    "id": "56",
                    "juan_int": "1",
                    "juan_name": "素问",
                    "zhang_jie_int": "56",
                    "zhang_jie_name": "皮部论"
                },
                {
                    "id": "57",
                    "juan_int": "1",
                    "juan_name": "素问",
                    "zhang_jie_int": "57",
                    "zhang_jie_name": "经络论"
                },
                {
                    "id": "58",
                    "juan_int": "1",
                    "juan_name": "素问",
                    "zhang_jie_int": "58",
                    "zhang_jie_name": "气穴论"
                },
                {
                    "id": "59",
                    "juan_int": "1",
                    "juan_name": "素问",
                    "zhang_jie_int": "59",
                    "zhang_jie_name": "气府论"
                },
                {
                    "id": "60",
                    "juan_int": "1",
                    "juan_name": "素问",
                    "zhang_jie_int": "60",
                    "zhang_jie_name": "骨空论"
                },
                {
                    "id": "61",
                    "juan_int": "1",
                    "juan_name": "素问",
                    "zhang_jie_int": "61",
                    "zhang_jie_name": "水热穴论"
                },
                {
                    "id": "62",
                    "juan_int": "1",
                    "juan_name": "素问",
                    "zhang_jie_int": "62",
                    "zhang_jie_name": "调经论"
                },
                {
                    "id": "63",
                    "juan_int": "1",
                    "juan_name": "素问",
                    "zhang_jie_int": "63",
                    "zhang_jie_name": "缪刺论"
                },
                {
                    "id": "64",
                    "juan_int": "1",
                    "juan_name": "素问",
                    "zhang_jie_int": "64",
                    "zhang_jie_name": "四时刺逆从论"
                },
                {
                    "id": "65",
                    "juan_int": "1",
                    "juan_name": "素问",
                    "zhang_jie_int": "65",
                    "zhang_jie_name": "标本病传论"
                },
                {
                    "id": "66",
                    "juan_int": "1",
                    "juan_name": "素问",
                    "zhang_jie_int": "66",
                    "zhang_jie_name": "天元纪大论"
                },
                {
                    "id": "67",
                    "juan_int": "1",
                    "juan_name": "素问",
                    "zhang_jie_int": "67",
                    "zhang_jie_name": "五运行大论"
                },
                {
                    "id": "68",
                    "juan_int": "1",
                    "juan_name": "素问",
                    "zhang_jie_int": "68",
                    "zhang_jie_name": "六微旨大论"
                },
                {
                    "id": "69",
                    "juan_int": "1",
                    "juan_name": "素问",
                    "zhang_jie_int": "69",
                    "zhang_jie_name": "气交变大论"
                },
                {
                    "id": "70",
                    "juan_int": "1",
                    "juan_name": "素问",
                    "zhang_jie_int": "70",
                    "zhang_jie_name": "五常政大论"
                },
                {
                    "id": "71",
                    "juan_int": "1",
                    "juan_name": "素问",
                    "zhang_jie_int": "71",
                    "zhang_jie_name": "六元正纪大论"
                },
                {
                    "id": "72",
                    "juan_int": "1",
                    "juan_name": "素问",
                    "zhang_jie_int": "72",
                    "zhang_jie_name": "刺法论"
                },
                {
                    "id": "73",
                    "juan_int": "1",
                    "juan_name": "素问",
                    "zhang_jie_int": "73",
                    "zhang_jie_name": "本病论"
                },
                {
                    "id": "74",
                    "juan_int": "1",
                    "juan_name": "素问",
                    "zhang_jie_int": "74",
                    "zhang_jie_name": "至真要大论"
                },
                {
                    "id": "75",
                    "juan_int": "1",
                    "juan_name": "素问",
                    "zhang_jie_int": "75",
                    "zhang_jie_name": "著至教论"
                },
                {
                    "id": "76",
                    "juan_int": "1",
                    "juan_name": "素问",
                    "zhang_jie_int": "76",
                    "zhang_jie_name": "示从容论"
                },
                {
                    "id": "77",
                    "juan_int": "1",
                    "juan_name": "素问",
                    "zhang_jie_int": "77",
                    "zhang_jie_name": "疏五过论"
                },
                {
                    "id": "78",
                    "juan_int": "1",
                    "juan_name": "素问",
                    "zhang_jie_int": "78",
                    "zhang_jie_name": "徵四失论"
                },
                {
                    "id": "79",
                    "juan_int": "1",
                    "juan_name": "素问",
                    "zhang_jie_int": "79",
                    "zhang_jie_name": "阴阳类论"
                },
                {
                    "id": "80",
                    "juan_int": "1",
                    "juan_name": "素问",
                    "zhang_jie_int": "80",
                    "zhang_jie_name": "方盛衰论"
                },
                {
                    "id": "81",
                    "juan_int": "1",
                    "juan_name": "素问",
                    "zhang_jie_int": "81",
                    "zhang_jie_name": "解精微论"
                }
            ]
        },
        {
            "juan_int": "2",
            "title": "灵枢",
            "zhang_jie": [
                {
                    "id": "82",
                    "juan_int": "2",
                    "juan_name": "灵枢",
                    "zhang_jie_int": "1",
                    "zhang_jie_name": "九针十二原"
                },
                {
                    "id": "83",
                    "juan_int": "2",
                    "juan_name": "灵枢",
                    "zhang_jie_int": "2",
                    "zhang_jie_name": "本输"
                },
                {
                    "id": "84",
                    "juan_int": "2",
                    "juan_name": "灵枢",
                    "zhang_jie_int": "3",
                    "zhang_jie_name": "小针解"
                },
                {
                    "id": "85",
                    "juan_int": "2",
                    "juan_name": "灵枢",
                    "zhang_jie_int": "4",
                    "zhang_jie_name": "邪气藏府病形"
                },
                {
                    "id": "86",
                    "juan_int": "2",
                    "juan_name": "灵枢",
                    "zhang_jie_int": "5",
                    "zhang_jie_name": "根结"
                },
                {
                    "id": "87",
                    "juan_int": "2",
                    "juan_name": "灵枢",
                    "zhang_jie_int": "6",
                    "zhang_jie_name": "寿夭刚柔"
                },
                {
                    "id": "88",
                    "juan_int": "2",
                    "juan_name": "灵枢",
                    "zhang_jie_int": "7",
                    "zhang_jie_name": "官针"
                },
                {
                    "id": "89",
                    "juan_int": "2",
                    "juan_name": "灵枢",
                    "zhang_jie_int": "8",
                    "zhang_jie_name": "本神"
                },
                {
                    "id": "90",
                    "juan_int": "2",
                    "juan_name": "灵枢",
                    "zhang_jie_int": "9",
                    "zhang_jie_name": "终始"
                },
                {
                    "id": "91",
                    "juan_int": "2",
                    "juan_name": "灵枢",
                    "zhang_jie_int": "10",
                    "zhang_jie_name": "经脉"
                },
                {
                    "id": "92",
                    "juan_int": "2",
                    "juan_name": "灵枢",
                    "zhang_jie_int": "11",
                    "zhang_jie_name": "经别"
                },
                {
                    "id": "93",
                    "juan_int": "2",
                    "juan_name": "灵枢",
                    "zhang_jie_int": "12",
                    "zhang_jie_name": "经水"
                },
                {
                    "id": "94",
                    "juan_int": "2",
                    "juan_name": "灵枢",
                    "zhang_jie_int": "13",
                    "zhang_jie_name": "经筋"
                },
                {
                    "id": "95",
                    "juan_int": "2",
                    "juan_name": "灵枢",
                    "zhang_jie_int": "14",
                    "zhang_jie_name": "骨度"
                },
                {
                    "id": "96",
                    "juan_int": "2",
                    "juan_name": "灵枢",
                    "zhang_jie_int": "15",
                    "zhang_jie_name": "五十营"
                },
                {
                    "id": "97",
                    "juan_int": "2",
                    "juan_name": "灵枢",
                    "zhang_jie_int": "16",
                    "zhang_jie_name": "营气"
                },
                {
                    "id": "98",
                    "juan_int": "2",
                    "juan_name": "灵枢",
                    "zhang_jie_int": "17",
                    "zhang_jie_name": "脉度"
                },
                {
                    "id": "99",
                    "juan_int": "2",
                    "juan_name": "灵枢",
                    "zhang_jie_int": "18",
                    "zhang_jie_name": "营卫生会"
                },
                {
                    "id": "100",
                    "juan_int": "2",
                    "juan_name": "灵枢",
                    "zhang_jie_int": "19",
                    "zhang_jie_name": "四时气"
                },
                {
                    "id": "101",
                    "juan_int": "2",
                    "juan_name": "灵枢",
                    "zhang_jie_int": "20",
                    "zhang_jie_name": "五邪"
                },
                {
                    "id": "102",
                    "juan_int": "2",
                    "juan_name": "灵枢",
                    "zhang_jie_int": "21",
                    "zhang_jie_name": "寒热病"
                },
                {
                    "id": "103",
                    "juan_int": "2",
                    "juan_name": "灵枢",
                    "zhang_jie_int": "22",
                    "zhang_jie_name": "癫狂"
                },
                {
                    "id": "104",
                    "juan_int": "2",
                    "juan_name": "灵枢",
                    "zhang_jie_int": "23",
                    "zhang_jie_name": "热病"
                },
                {
                    "id": "105",
                    "juan_int": "2",
                    "juan_name": "灵枢",
                    "zhang_jie_int": "24",
                    "zhang_jie_name": "厥病"
                },
                {
                    "id": "106",
                    "juan_int": "2",
                    "juan_name": "灵枢",
                    "zhang_jie_int": "25",
                    "zhang_jie_name": "病本"
                },
                {
                    "id": "107",
                    "juan_int": "2",
                    "juan_name": "灵枢",
                    "zhang_jie_int": "26",
                    "zhang_jie_name": "杂病"
                },
                {
                    "id": "108",
                    "juan_int": "2",
                    "juan_name": "灵枢",
                    "zhang_jie_int": "27",
                    "zhang_jie_name": "周痹"
                },
                {
                    "id": "109",
                    "juan_int": "2",
                    "juan_name": "灵枢",
                    "zhang_jie_int": "28",
                    "zhang_jie_name": "口问"
                },
                {
                    "id": "110",
                    "juan_int": "2",
                    "juan_name": "灵枢",
                    "zhang_jie_int": "29",
                    "zhang_jie_name": "师传"
                },
                {
                    "id": "111",
                    "juan_int": "2",
                    "juan_name": "灵枢",
                    "zhang_jie_int": "30",
                    "zhang_jie_name": "决气"
                },
                {
                    "id": "112",
                    "juan_int": "2",
                    "juan_name": "灵枢",
                    "zhang_jie_int": "31",
                    "zhang_jie_name": "肠胃"
                },
                {
                    "id": "113",
                    "juan_int": "2",
                    "juan_name": "灵枢",
                    "zhang_jie_int": "32",
                    "zhang_jie_name": "平人绝谷"
                },
                {
                    "id": "114",
                    "juan_int": "2",
                    "juan_name": "灵枢",
                    "zhang_jie_int": "33",
                    "zhang_jie_name": "海论"
                },
                {
                    "id": "115",
                    "juan_int": "2",
                    "juan_name": "灵枢",
                    "zhang_jie_int": "34",
                    "zhang_jie_name": "五乱"
                },
                {
                    "id": "116",
                    "juan_int": "2",
                    "juan_name": "灵枢",
                    "zhang_jie_int": "35",
                    "zhang_jie_name": "胀论"
                },
                {
                    "id": "117",
                    "juan_int": "2",
                    "juan_name": "灵枢",
                    "zhang_jie_int": "36",
                    "zhang_jie_name": "五癃津液别"
                },
                {
                    "id": "118",
                    "juan_int": "2",
                    "juan_name": "灵枢",
                    "zhang_jie_int": "37",
                    "zhang_jie_name": "五阅五使"
                },
                {
                    "id": "119",
                    "juan_int": "2",
                    "juan_name": "灵枢",
                    "zhang_jie_int": "38",
                    "zhang_jie_name": "逆顺肥瘦"
                },
                {
                    "id": "120",
                    "juan_int": "2",
                    "juan_name": "灵枢",
                    "zhang_jie_int": "39",
                    "zhang_jie_name": "血络论"
                },
                {
                    "id": "121",
                    "juan_int": "2",
                    "juan_name": "灵枢",
                    "zhang_jie_int": "40",
                    "zhang_jie_name": "阴阳清浊"
                },
                {
                    "id": "122",
                    "juan_int": "2",
                    "juan_name": "灵枢",
                    "zhang_jie_int": "41",
                    "zhang_jie_name": "阴阳系日月"
                },
                {
                    "id": "123",
                    "juan_int": "2",
                    "juan_name": "灵枢",
                    "zhang_jie_int": "42",
                    "zhang_jie_name": "病传"
                },
                {
                    "id": "124",
                    "juan_int": "2",
                    "juan_name": "灵枢",
                    "zhang_jie_int": "43",
                    "zhang_jie_name": "淫邪发梦"
                },
                {
                    "id": "125",
                    "juan_int": "2",
                    "juan_name": "灵枢",
                    "zhang_jie_int": "44",
                    "zhang_jie_name": "顺气一日分为四时"
                },
                {
                    "id": "126",
                    "juan_int": "2",
                    "juan_name": "灵枢",
                    "zhang_jie_int": "45",
                    "zhang_jie_name": "外揣"
                },
                {
                    "id": "127",
                    "juan_int": "2",
                    "juan_name": "灵枢",
                    "zhang_jie_int": "46",
                    "zhang_jie_name": "五变"
                },
                {
                    "id": "128",
                    "juan_int": "2",
                    "juan_name": "灵枢",
                    "zhang_jie_int": "47",
                    "zhang_jie_name": "本藏"
                },
                {
                    "id": "129",
                    "juan_int": "2",
                    "juan_name": "灵枢",
                    "zhang_jie_int": "48",
                    "zhang_jie_name": "禁服"
                },
                {
                    "id": "130",
                    "juan_int": "2",
                    "juan_name": "灵枢",
                    "zhang_jie_int": "49",
                    "zhang_jie_name": "五色"
                },
                {
                    "id": "131",
                    "juan_int": "2",
                    "juan_name": "灵枢",
                    "zhang_jie_int": "50",
                    "zhang_jie_name": "论勇"
                },
                {
                    "id": "132",
                    "juan_int": "2",
                    "juan_name": "灵枢",
                    "zhang_jie_int": "51",
                    "zhang_jie_name": "背俞"
                },
                {
                    "id": "133",
                    "juan_int": "2",
                    "juan_name": "灵枢",
                    "zhang_jie_int": "52",
                    "zhang_jie_name": "卫气"
                },
                {
                    "id": "134",
                    "juan_int": "2",
                    "juan_name": "灵枢",
                    "zhang_jie_int": "53",
                    "zhang_jie_name": "论痛"
                },
                {
                    "id": "135",
                    "juan_int": "2",
                    "juan_name": "灵枢",
                    "zhang_jie_int": "54",
                    "zhang_jie_name": "天年"
                },
                {
                    "id": "136",
                    "juan_int": "2",
                    "juan_name": "灵枢",
                    "zhang_jie_int": "55",
                    "zhang_jie_name": "逆顺"
                },
                {
                    "id": "137",
                    "juan_int": "2",
                    "juan_name": "灵枢",
                    "zhang_jie_int": "56",
                    "zhang_jie_name": "五味"
                },
                {
                    "id": "138",
                    "juan_int": "2",
                    "juan_name": "灵枢",
                    "zhang_jie_int": "57",
                    "zhang_jie_name": "水胀"
                },
                {
                    "id": "139",
                    "juan_int": "2",
                    "juan_name": "灵枢",
                    "zhang_jie_int": "58",
                    "zhang_jie_name": "贼风"
                },
                {
                    "id": "140",
                    "juan_int": "2",
                    "juan_name": "灵枢",
                    "zhang_jie_int": "59",
                    "zhang_jie_name": "卫气失常"
                },
                {
                    "id": "141",
                    "juan_int": "2",
                    "juan_name": "灵枢",
                    "zhang_jie_int": "60",
                    "zhang_jie_name": "玉版"
                },
                {
                    "id": "142",
                    "juan_int": "2",
                    "juan_name": "灵枢",
                    "zhang_jie_int": "61",
                    "zhang_jie_name": "五禁"
                },
                {
                    "id": "143",
                    "juan_int": "2",
                    "juan_name": "灵枢",
                    "zhang_jie_int": "62",
                    "zhang_jie_name": "动输"
                },
                {
                    "id": "144",
                    "juan_int": "2",
                    "juan_name": "灵枢",
                    "zhang_jie_int": "63",
                    "zhang_jie_name": "五味论"
                },
                {
                    "id": "145",
                    "juan_int": "2",
                    "juan_name": "灵枢",
                    "zhang_jie_int": "64",
                    "zhang_jie_name": "阴阳二十五人"
                },
                {
                    "id": "146",
                    "juan_int": "2",
                    "juan_name": "灵枢",
                    "zhang_jie_int": "65",
                    "zhang_jie_name": "五音五味"
                },
                {
                    "id": "147",
                    "juan_int": "2",
                    "juan_name": "灵枢",
                    "zhang_jie_int": "66",
                    "zhang_jie_name": "百病始生"
                },
                {
                    "id": "148",
                    "juan_int": "2",
                    "juan_name": "灵枢",
                    "zhang_jie_int": "67",
                    "zhang_jie_name": "行针"
                },
                {
                    "id": "149",
                    "juan_int": "2",
                    "juan_name": "灵枢",
                    "zhang_jie_int": "68",
                    "zhang_jie_name": "上隔"
                },
                {
                    "id": "150",
                    "juan_int": "2",
                    "juan_name": "灵枢",
                    "zhang_jie_int": "69",
                    "zhang_jie_name": "忧患无言"
                },
                {
                    "id": "151",
                    "juan_int": "2",
                    "juan_name": "灵枢",
                    "zhang_jie_int": "70",
                    "zhang_jie_name": "寒热"
                },
                {
                    "id": "152",
                    "juan_int": "2",
                    "juan_name": "灵枢",
                    "zhang_jie_int": "71",
                    "zhang_jie_name": "邪客"
                },
                {
                    "id": "153",
                    "juan_int": "2",
                    "juan_name": "灵枢",
                    "zhang_jie_int": "72",
                    "zhang_jie_name": "通天"
                },
                {
                    "id": "154",
                    "juan_int": "2",
                    "juan_name": "灵枢",
                    "zhang_jie_int": "73",
                    "zhang_jie_name": "官能"
                },
                {
                    "id": "155",
                    "juan_int": "2",
                    "juan_name": "灵枢",
                    "zhang_jie_int": "74",
                    "zhang_jie_name": "论疾诊尺"
                },
                {
                    "id": "156",
                    "juan_int": "2",
                    "juan_name": "灵枢",
                    "zhang_jie_int": "75",
                    "zhang_jie_name": "刺节真邪"
                },
                {
                    "id": "157",
                    "juan_int": "2",
                    "juan_name": "灵枢",
                    "zhang_jie_int": "76",
                    "zhang_jie_name": "卫气行"
                },
                {
                    "id": "158",
                    "juan_int": "2",
                    "juan_name": "灵枢",
                    "zhang_jie_int": "77",
                    "zhang_jie_name": "九宫八风"
                },
                {
                    "id": "159",
                    "juan_int": "2",
                    "juan_name": "灵枢",
                    "zhang_jie_int": "78",
                    "zhang_jie_name": "九针论"
                },
                {
                    "id": "160",
                    "juan_int": "2",
                    "juan_name": "灵枢",
                    "zhang_jie_int": "79",
                    "zhang_jie_name": "岁露论"
                },
                {
                    "id": "161",
                    "juan_int": "2",
                    "juan_name": "灵枢",
                    "zhang_jie_int": "80",
                    "zhang_jie_name": "大惑论"
                },
                {
                    "id": "162",
                    "juan_int": "2",
                    "juan_name": "灵枢",
                    "zhang_jie_int": "81",
                    "zhang_jie_name": "痈疽"
                }
            ]
        }
    ]
}